ruth_tts/__init__.py
ruth_tts/api.py
ruth_TTS-0.0.3.dist-info/METADATA
ruth_TTS-0.0.3.dist-info/WHEEL
ruth_TTS-0.0.3.dist-info/entry_points.txt
ruth_TTS-0.0.3.dist-info/top_level.txt
ruth_TTS-0.0.3.dist-info/RECORD
