Metadata-Version: 2.1
Name: ruth-TTS
Version: 0.0.3
Summary: PYTHON LIBRARY FOR RUTH-TTS
Home-page: 
Author: puratalk
Author-email: info@puretalk.ai
License: UNKNOWN
Platform: UNKNOWN
Classifier: Development Status :: 3 - Alpha
Classifier: Intended Audience :: Developers
Classifier: Topic :: Software Development :: Build Tools
Classifier: Programming Language :: Python :: 3.8
Requires-Python: >=3.7,<3.9
Requires-Dist: requests (~=2.23.0)
